flashbots/__init__.py
flashbots/flashbots.py
flashbots/middleware.py
flashbots/provider.py
flashbots/types.py
open_aea_flashbots-2.0.0.dist-info/LICENSE
open_aea_flashbots-2.0.0.dist-info/METADATA
open_aea_flashbots-2.0.0.dist-info/WHEEL
open_aea_flashbots-2.0.0.dist-info/RECORD
