Metadata-Version: 2.3
Name: open-aea-flashbots
Version: 2.0.0
Summary: 
Author: Georgios Konstantopoulos
Author-email: me@gakonst.com
Requires-Python: >=3.9,<4.0
Classifier: Programming Language :: Python :: 3
Classifier: Programming Language :: Python :: 3.9
Classifier: Programming Language :: Python :: 3.10
Classifier: Programming Language :: Python :: 3.11
Classifier: Programming Language :: Python :: 3.12
Classifier: Programming Language :: Python :: 3.13
Requires-Dist: web3 (>=7,<8)
